cccscrapper/__init__.py
cccscrapper/crawl.py
cccscrapper/get_structure.py
cccscrapper/validate_crawl.py
cccscrapper/validate_get_structure.py
cccscrapper-0.1.1.dist-info/licenses/LICENSE
cccscrapper-0.1.1.dist-info/METADATA
cccscrapper-0.1.1.dist-info/WHEEL
cccscrapper-0.1.1.dist-info/top_level.txt
cccscrapper-0.1.1.dist-info/RECORD
